{
  "metadata": {
    "schema_version": "1.0.0",
    "source": "historico-disciplina-filtered.csv",
    "generated_at": "2026-01-25T19:29:53.932Z",
    "total_disciplinas": 43,
    "calculation_methodology": {
      "idd_formula": "0.35*TR + 0.20*TA + 0.20*NM_d + 0.15*PNB + 0.10*CH",
      "normalization_threshold_ch": 0.25,
      "low_grade_cutoff": 60,
      "components": {
        "TR": "componentes_idd.taxa_reprovacao_global",
        "TA": "componentes_idd.taxa_abandono_global",
        "NM": "componentes_idd.media_nota_global",
        "NM_d": "componentes_idd.media_nota_normalizada",
        "PNB": "componentes_idd.proporcao_notas_baixas",
        "CH": "componentes_idd.consistencia_historica.valor_normalizado"
      },
      "redundancy_policy": "indicadores contains final values for API consumption; componentes_idd contains intermediate calculations for auditability"
    }
  },
  "endpoints": {
    "/disciplinas": [
      {
        "codigo_disciplina": "ADE 104",
        "disciplina": "TEORIA GERAL DA ADMINISTRAÇÃO",
        "carga_horaria": 60,
        "dados_agregados": {
          "total_estudantes": 3094,
          "aprovacoes": 2549,
          "reprovacoes": 355,
          "abandonos": 190,
          "media_nota_global": 65.77,
          "menor_nota_global": 3,
          "maior_nota_global": 100
        },
        "componentes_idd": {
          "taxa_reprovacao_global": 0.1147,
          "taxa_abandono_global": 0.0614,
          "media_nota_global": 65.77,
          "media_nota_normalizada": 0.3423,
          "proporcao_notas_baixas": 0.2292,
          "consistencia_historica": {
            "valor_normalizado": 0.7085,
            "desvio_padrao_tr": 0.0729,
            "limiar_normalizacao": 0.25
          }
        },
        "indicadores": {
          "taxa_reprovacao": 0.1147,
          "taxa_abandono": 0.0614,
          "proporcao_notas_baixas": 0.2292,
          "consistencia_historica": 0.7085,
          "indice_dificuldade": 0.2261
        },
        "distribuicao_notas_global": {
          "0_10": 196,
          "10_20": 51,
          "20_30": 47,
          "30_40": 68,
          "40_50": 93,
          "50_60": 254,
          "60_70": 734,
          "70_80": 918,
          "80_90": 561,
          "90_100": 0
        }
      },
      {
        "codigo_disciplina": "ADE 190",
        "disciplina": "INTRODUÇÃO À ECONOMIA",
        "carga_horaria": 60,
        "dados_agregados": {
          "total_estudantes": 2890,
          "aprovacoes": 2407,
          "reprovacoes": 366,
          "abandonos": 117,
          "media_nota_global": 68.95,
          "menor_nota_global": 1,
          "maior_nota_global": 100
        },
        "componentes_idd": {
          "taxa_reprovacao_global": 0.1266,
          "taxa_abandono_global": 0.0405,
          "media_nota_global": 68.95,
          "media_nota_normalizada": 0.3105,
          "proporcao_notas_baixas": 0.2412,
          "consistencia_historica": {
            "valor_normalizado": 0.6942,
            "desvio_padrao_tr": 0.0765,
            "limiar_normalizacao": 0.25
          }
        },
        "indicadores": {
          "taxa_reprovacao": 0.1266,
          "taxa_abandono": 0.0405,
          "proporcao_notas_baixas": 0.2412,
          "consistencia_historica": 0.6942,
          "indice_dificuldade": 0.2201
        },
        "distribuicao_notas_global": {
          "0_10": 105,
          "10_20": 49,
          "20_30": 51,
          "30_40": 70,
          "40_50": 107,
          "50_60": 315,
          "60_70": 629,
          "70_80": 675,
          "80_90": 490,
          "90_100": 0
        }
      },
      {
        "codigo_disciplina": "ADE 327",
        "disciplina": "EMPREENDEDORISMO",
        "carga_horaria": 60,
        "dados_agregados": {
          "total_estudantes": 1054,
          "aprovacoes": 990,
          "reprovacoes": 36,
          "abandonos": 28,
          "media_nota_global": 75.06,
          "menor_nota_global": 10,
          "maior_nota_global": 100
        },
        "componentes_idd": {
          "taxa_reprovacao_global": 0.0342,
          "taxa_abandono_global": 0.0266,
          "media_nota_global": 75.06,
          "media_nota_normalizada": 0.2494,
          "proporcao_notas_baixas": 0.0901,
          "consistencia_historica": {
            "valor_normalizado": 0.874,
            "desvio_padrao_tr": 0.0315,
            "limiar_normalizacao": 0.25
          }
        },
        "indicadores": {
          "taxa_reprovacao": 0.0342,
          "taxa_abandono": 0.0266,
          "proporcao_notas_baixas": 0.0901,
          "consistencia_historica": 0.874,
          "indice_dificuldade": 0.1681
        },
        "distribuicao_notas_global": {
          "0_10": 23,
          "10_20": 9,
          "20_30": 10,
          "30_40": 7,
          "40_50": 5,
          "50_60": 41,
          "60_70": 176,
          "70_80": 321,
          "80_90": 344,
          "90_100": 0
        }
      },
      {
        "codigo_disciplina": "CIC 100",
        "disciplina": "CONTABILIDADE GERAL",
        "carga_horaria": 60,
        "dados_agregados": {
          "total_estudantes": 3383,
          "aprovacoes": 1944,
          "reprovacoes": 977,
          "abandonos": 462,
          "media_nota_global": 53.7,
          "menor_nota_global": 1,
          "maior_nota_global": 100
        },
        "componentes_idd": {
          "taxa_reprovacao_global": 0.2888,
          "taxa_abandono_global": 0.1366,
          "media_nota_global": 53.7,
          "media_nota_normalizada": 0.463,
          "proporcao_notas_baixas": 0.4753,
          "consistencia_historica": {
            "valor_normalizado": 0.7086,
            "desvio_padrao_tr": 0.0729,
            "limiar_normalizacao": 0.25
          }
        },
        "indicadores": {
          "taxa_reprovacao": 0.2888,
          "taxa_abandono": 0.1366,
          "proporcao_notas_baixas": 0.4753,
          "consistencia_historica": 0.7086,
          "indice_dificuldade": 0.3632
        },
        "distribuicao_notas_global": {
          "0_10": 337,
          "10_20": 240,
          "20_30": 234,
          "30_40": 231,
          "40_50": 214,
          "50_60": 352,
          "60_70": 673,
          "70_80": 567,
          "80_90": 334,
          "90_100": 0
        }
      },
      {
        "codigo_disciplina": "CRP 199",
        "disciplina": "CÁLCULO DIFERENCIAL E INTEGRAL",
        "carga_horaria": 90,
        "dados_agregados": {
          "total_estudantes": 3675,
          "aprovacoes": 1295,
          "reprovacoes": 1950,
          "abandonos": 430,
          "media_nota_global": 36.6,
          "menor_nota_global": 1,
          "maior_nota_global": 100
        },
        "componentes_idd": {
          "taxa_reprovacao_global": 0.5306,
          "taxa_abandono_global": 0.117,
          "media_nota_global": 36.6,
          "media_nota_normalizada": 0.634,
          "proporcao_notas_baixas": 0.7317,
          "consistencia_historica": {
            "valor_normalizado": 0.7003,
            "desvio_padrao_tr": 0.0749,
            "limiar_normalizacao": 0.25
          }
        },
        "indicadores": {
          "taxa_reprovacao": 0.5306,
          "taxa_abandono": 0.117,
          "proporcao_notas_baixas": 0.7317,
          "consistencia_historica": 0.7003,
          "indice_dificuldade": 0.5157
        },
        "distribuicao_notas_global": {
          "0_10": 991,
          "10_20": 421,
          "20_30": 321,
          "30_40": 275,
          "40_50": 220,
          "50_60": 461,
          "60_70": 491,
          "70_80": 283,
          "80_90": 145,
          "90_100": 0
        }
      },
      {
        "codigo_disciplina": "CRP 199",
        "disciplina": "CÁLCULO I",
        "carga_horaria": 90,
        "dados_agregados": {
          "total_estudantes": 1329,
          "aprovacoes": 454,
          "reprovacoes": 621,
          "abandonos": 254,
          "media_nota_global": 36.68,
          "menor_nota_global": 1,
          "maior_nota_global": 100
        },
        "componentes_idd": {
          "taxa_reprovacao_global": 0.4673,
          "taxa_abandono_global": 0.1911,
          "media_nota_global": 36.68,
          "media_nota_normalizada": 0.6332,
          "proporcao_notas_baixas": 0.7073,
          "consistencia_historica": {
            "valor_normalizado": 0.1287,
            "desvio_padrao_tr": 0.2178,
            "limiar_normalizacao": 0.25
          }
        },
        "indicadores": {
          "taxa_reprovacao": 0.4673,
          "taxa_abandono": 0.1911,
          "proporcao_notas_baixas": 0.7073,
          "consistencia_historica": 0.1287,
          "indice_dificuldade": 0.4474
        },
        "distribuicao_notas_global": {
          "0_10": 347,
          "10_20": 133,
          "20_30": 173,
          "30_40": 106,
          "40_50": 59,
          "50_60": 122,
          "60_70": 187,
          "70_80": 134,
          "80_90": 57,
          "90_100": 0
        }
      },
      {
        "codigo_disciplina": "CRP 297",
        "disciplina": "SOCIOLOGIA GERAL",
        "carga_horaria": 60,
        "dados_agregados": {
          "total_estudantes": 5554,
          "aprovacoes": 3708,
          "reprovacoes": 1418,
          "abandonos": 428,
          "media_nota_global": 58.46,
          "menor_nota_global": 2,
          "maior_nota_global": 100
        },
        "componentes_idd": {
          "taxa_reprovacao_global": 0.2553,
          "taxa_abandono_global": 0.0771,
          "media_nota_global": 58.46,
          "media_nota_normalizada": 0.4154,
          "proporcao_notas_baixas": 0.4073,
          "consistencia_historica": {
            "valor_normalizado": 0.5811,
            "desvio_padrao_tr": 0.1047,
            "limiar_normalizacao": 0.25
          }
        },
        "indicadores": {
          "taxa_reprovacao": 0.2553,
          "taxa_abandono": 0.0771,
          "proporcao_notas_baixas": 0.4073,
          "consistencia_historica": 0.5811,
          "indice_dificuldade": 0.3071
        },
        "distribuicao_notas_global": {
          "0_10": 513,
          "10_20": 222,
          "20_30": 250,
          "30_40": 225,
          "40_50": 310,
          "50_60": 742,
          "60_70": 1156,
          "70_80": 1021,
          "80_90": 791,
          "90_100": 0
        }
      },
      {
        "codigo_disciplina": "CRP 298",
        "disciplina": "GEOMETRIA ANALÍTICA E ÁLGEBRA LINEAR",
        "carga_horaria": 60,
        "dados_agregados": {
          "total_estudantes": 2811,
          "aprovacoes": 1272,
          "reprovacoes": 1282,
          "abandonos": 257,
          "media_nota_global": 44.86,
          "menor_nota_global": 1,
          "maior_nota_global": 100
        },
        "componentes_idd": {
          "taxa_reprovacao_global": 0.4561,
          "taxa_abandono_global": 0.0914,
          "media_nota_global": 44.86,
          "media_nota_normalizada": 0.5514,
          "proporcao_notas_baixas": 0.6101,
          "consistencia_historica": {
            "valor_normalizado": 0.511,
            "desvio_padrao_tr": 0.1223,
            "limiar_normalizacao": 0.25
          }
        },
        "indicadores": {
          "taxa_reprovacao": 0.4561,
          "taxa_abandono": 0.0914,
          "proporcao_notas_baixas": 0.6101,
          "consistencia_historica": 0.511,
          "indice_dificuldade": 0.4308
        },
        "distribuicao_notas_global": {
          "0_10": 440,
          "10_20": 301,
          "20_30": 222,
          "30_40": 197,
          "40_50": 194,
          "50_60": 361,
          "60_70": 589,
          "70_80": 327,
          "80_90": 113,
          "90_100": 0
        }
      },
      {
        "codigo_disciplina": "ESP 105",
        "disciplina": "INICIAÇÃO À ESTATÍSTICA",
        "carga_horaria": 60,
        "dados_agregados": {
          "total_estudantes": 324,
          "aprovacoes": 235,
          "reprovacoes": 76,
          "abandonos": 13,
          "media_nota_global": 60.02,
          "menor_nota_global": 2,
          "maior_nota_global": 100
        },
        "componentes_idd": {
          "taxa_reprovacao_global": 0.2346,
          "taxa_abandono_global": 0.0401,
          "media_nota_global": 60.02,
          "media_nota_normalizada": 0.3998,
          "proporcao_notas_baixas": 0.3457,
          "consistencia_historica": {
            "valor_normalizado": 0.7321,
            "desvio_padrao_tr": 0.067,
            "limiar_normalizacao": 0.25
          }
        },
        "indicadores": {
          "taxa_reprovacao": 0.2346,
          "taxa_abandono": 0.0401,
          "proporcao_notas_baixas": 0.3457,
          "consistencia_historica": 0.7321,
          "indice_dificuldade": 0.2951
        },
        "distribuicao_notas_global": {
          "0_10": 22,
          "10_20": 8,
          "20_30": 10,
          "30_40": 11,
          "40_50": 14,
          "50_60": 47,
          "60_70": 100,
          "70_80": 72,
          "80_90": 34,
          "90_100": 0
        }
      },
      {
        "codigo_disciplina": "SIN 100",
        "disciplina": "TRATAMENTO E ANÁLISE DE DADOS/INFORMAÇÕES",
        "carga_horaria": 60,
        "dados_agregados": {
          "total_estudantes": 765,
          "aprovacoes": 601,
          "reprovacoes": 92,
          "abandonos": 72,
          "media_nota_global": 62.18,
          "menor_nota_global": 4,
          "maior_nota_global": 99
        },
        "componentes_idd": {
          "taxa_reprovacao_global": 0.1203,
          "taxa_abandono_global": 0.0941,
          "media_nota_global": 62.18,
          "media_nota_normalizada": 0.3782,
          "proporcao_notas_baixas": 0.2588,
          "consistencia_historica": {
            "valor_normalizado": 0.5735,
            "desvio_padrao_tr": 0.1066,
            "limiar_normalizacao": 0.25
          }
        },
        "indicadores": {
          "taxa_reprovacao": 0.1203,
          "taxa_abandono": 0.0941,
          "proporcao_notas_baixas": 0.2588,
          "consistencia_historica": 0.5735,
          "indice_dificuldade": 0.2327
        },
        "distribuicao_notas_global": {
          "0_10": 89,
          "10_20": 22,
          "20_30": 24,
          "30_40": 7,
          "40_50": 9,
          "50_60": 47,
          "60_70": 172,
          "70_80": 208,
          "80_90": 148,
          "90_100": 0
        }
      },
      {
        "codigo_disciplina": "SIN 101",
        "disciplina": "INFORMÁTICA E SOCIEDADE",
        "carga_horaria": 30,
        "dados_agregados": {
          "total_estudantes": 1109,
          "aprovacoes": 940,
          "reprovacoes": 77,
          "abandonos": 92,
          "media_nota_global": 71.72,
          "menor_nota_global": 4,
          "maior_nota_global": 100
        },
        "componentes_idd": {
          "taxa_reprovacao_global": 0.0694,
          "taxa_abandono_global": 0.083,
          "media_nota_global": 71.72,
          "media_nota_normalizada": 0.2828,
          "proporcao_notas_baixas": 0.1713,
          "consistencia_historica": {
            "valor_normalizado": 0.8025,
            "desvio_padrao_tr": 0.0494,
            "limiar_normalizacao": 0.25
          }
        },
        "indicadores": {
          "taxa_reprovacao": 0.0694,
          "taxa_abandono": 0.083,
          "proporcao_notas_baixas": 0.1713,
          "consistencia_historica": 0.8025,
          "indice_dificuldade": 0.2034
        },
        "distribuicao_notas_global": {
          "0_10": 86,
          "10_20": 14,
          "20_30": 15,
          "30_40": 18,
          "40_50": 15,
          "50_60": 42,
          "60_70": 137,
          "70_80": 240,
          "80_90": 316,
          "90_100": 0
        }
      },
      {
        "codigo_disciplina": "SIN 110",
        "disciplina": "PROGRAMAÇÃO I",
        "carga_horaria": 90,
        "dados_agregados": {
          "total_estudantes": 569,
          "aprovacoes": 266,
          "reprovacoes": 242,
          "abandonos": 61,
          "media_nota_global": 44.77,
          "menor_nota_global": 1,
          "maior_nota_global": 100
        },
        "componentes_idd": {
          "taxa_reprovacao_global": 0.4253,
          "taxa_abandono_global": 0.1072,
          "media_nota_global": 44.77,
          "media_nota_normalizada": 0.5523,
          "proporcao_notas_baixas": 0.5694,
          "consistencia_historica": {
            "valor_normalizado": 0.7663,
            "desvio_padrao_tr": 0.0584,
            "limiar_normalizacao": 0.25
          }
        },
        "indicadores": {
          "taxa_reprovacao": 0.4253,
          "taxa_abandono": 0.1072,
          "proporcao_notas_baixas": 0.5694,
          "consistencia_historica": 0.7663,
          "indice_dificuldade": 0.4428
        },
        "distribuicao_notas_global": {
          "0_10": 105,
          "10_20": 67,
          "20_30": 42,
          "30_40": 48,
          "40_50": 24,
          "50_60": 38,
          "60_70": 94,
          "70_80": 84,
          "80_90": 48,
          "90_100": 0
        }
      },
      {
        "codigo_disciplina": "SIN 110",
        "disciplina": "PROGRAMAÇÃO",
        "carga_horaria": 90,
        "dados_agregados": {
          "total_estudantes": 3111,
          "aprovacoes": 1246,
          "reprovacoes": 1487,
          "abandonos": 378,
          "media_nota_global": 41.19,
          "menor_nota_global": 1,
          "maior_nota_global": 99
        },
        "componentes_idd": {
          "taxa_reprovacao_global": 0.478,
          "taxa_abandono_global": 0.1215,
          "media_nota_global": 41.19,
          "media_nota_normalizada": 0.5881,
          "proporcao_notas_baixas": 0.6522,
          "consistencia_historica": {
            "valor_normalizado": 0.4201,
            "desvio_padrao_tr": 0.145,
            "limiar_normalizacao": 0.25
          }
        },
        "indicadores": {
          "taxa_reprovacao": 0.478,
          "taxa_abandono": 0.1215,
          "proporcao_notas_baixas": 0.6522,
          "consistencia_historica": 0.4201,
          "indice_dificuldade": 0.449
        },
        "distribuicao_notas_global": {
          "0_10": 646,
          "10_20": 347,
          "20_30": 318,
          "30_40": 228,
          "40_50": 213,
          "50_60": 277,
          "60_70": 460,
          "70_80": 336,
          "80_90": 210,
          "90_100": 0
        }
      },
      {
        "codigo_disciplina": "SIN 130",
        "disciplina": "INTRODUÇÃO À LÓGICA",
        "carga_horaria": 60,
        "dados_agregados": {
          "total_estudantes": 1694,
          "aprovacoes": 992,
          "reprovacoes": 587,
          "abandonos": 115,
          "media_nota_global": 54.62,
          "menor_nota_global": 1,
          "maior_nota_global": 100
        },
        "componentes_idd": {
          "taxa_reprovacao_global": 0.3465,
          "taxa_abandono_global": 0.0679,
          "media_nota_global": 54.62,
          "media_nota_normalizada": 0.4538,
          "proporcao_notas_baixas": 0.4687,
          "consistencia_historica": {
            "valor_normalizado": 0.5713,
            "desvio_padrao_tr": 0.1072,
            "limiar_normalizacao": 0.25
          }
        },
        "indicadores": {
          "taxa_reprovacao": 0.3465,
          "taxa_abandono": 0.0679,
          "proporcao_notas_baixas": 0.4687,
          "consistencia_historica": 0.5713,
          "indice_dificuldade": 0.3531
        },
        "distribuicao_notas_global": {
          "0_10": 134,
          "10_20": 113,
          "20_30": 122,
          "30_40": 143,
          "40_50": 109,
          "50_60": 173,
          "60_70": 335,
          "70_80": 291,
          "80_90": 190,
          "90_100": 0
        }
      },
      {
        "codigo_disciplina": "SIN 131",
        "disciplina": "INTRODUÇÃO À TEORIA DA COMPUTAÇÃO",
        "carga_horaria": 60,
        "dados_agregados": {
          "total_estudantes": 406,
          "aprovacoes": 266,
          "reprovacoes": 122,
          "abandonos": 18,
          "media_nota_global": 56.33,
          "menor_nota_global": 1,
          "maior_nota_global": 100
        },
        "componentes_idd": {
          "taxa_reprovacao_global": 0.3005,
          "taxa_abandono_global": 0.0443,
          "media_nota_global": 56.33,
          "media_nota_normalizada": 0.4367,
          "proporcao_notas_baixas": 0.4409,
          "consistencia_historica": {
            "valor_normalizado": 0.244,
            "desvio_padrao_tr": 0.189,
            "limiar_normalizacao": 0.25
          }
        },
        "indicadores": {
          "taxa_reprovacao": 0.3005,
          "taxa_abandono": 0.0443,
          "proporcao_notas_baixas": 0.4409,
          "consistencia_historica": 0.244,
          "indice_dificuldade": 0.2919
        },
        "distribuicao_notas_global": {
          "0_10": 28,
          "10_20": 31,
          "20_30": 21,
          "30_40": 25,
          "40_50": 16,
          "50_60": 58,
          "60_70": 95,
          "70_80": 72,
          "80_90": 40,
          "90_100": 0
        }
      },
      {
        "codigo_disciplina": "SIN 131",
        "disciplina": "INTRODUÇÃO À TEORIA DA COMPUTAÇÃO I",
        "carga_horaria": 60,
        "dados_agregados": {
          "total_estudantes": 10,
          "aprovacoes": 10,
          "reprovacoes": 0,
          "abandonos": 0,
          "media_nota_global": 85.7,
          "menor_nota_global": 70,
          "maior_nota_global": 97
        },
        "componentes_idd": {
          "taxa_reprovacao_global": 0,
          "taxa_abandono_global": 0,
          "media_nota_global": 85.7,
          "media_nota_normalizada": 0.143,
          "proporcao_notas_baixas": 0,
          "consistencia_historica": {
            "valor_normalizado": 1,
            "desvio_padrao_tr": 0,
            "limiar_normalizacao": 0.25
          }
        },
        "indicadores": {
          "taxa_reprovacao": 0,
          "taxa_abandono": 0,
          "proporcao_notas_baixas": 0,
          "consistencia_historica": 1,
          "indice_dificuldade": 0.1286
        },
        "distribuicao_notas_global": {
          "0_10": 0,
          "10_20": 0,
          "20_30": 0,
          "30_40": 0,
          "40_50": 0,
          "50_60": 0,
          "60_70": 1,
          "70_80": 2,
          "80_90": 4,
          "90_100": 0
        }
      },
      {
        "codigo_disciplina": "SIN 131",
        "disciplina": "INTRODUÇÃO À TEORIA DA  COMPUTAÇÃO",
        "carga_horaria": 60,
        "dados_agregados": {
          "total_estudantes": 198,
          "aprovacoes": 151,
          "reprovacoes": 43,
          "abandonos": 4,
          "media_nota_global": 59.28,
          "menor_nota_global": 1,
          "maior_nota_global": 97
        },
        "componentes_idd": {
          "taxa_reprovacao_global": 0.2172,
          "taxa_abandono_global": 0.0202,
          "media_nota_global": 59.28,
          "media_nota_normalizada": 0.4072,
          "proporcao_notas_baixas": 0.404,
          "consistencia_historica": {
            "valor_normalizado": 0.5092,
            "desvio_padrao_tr": 0.1227,
            "limiar_normalizacao": 0.25
          }
        },
        "indicadores": {
          "taxa_reprovacao": 0.2172,
          "taxa_abandono": 0.0202,
          "proporcao_notas_baixas": 0.404,
          "consistencia_historica": 0.5092,
          "indice_dificuldade": 0.273
        },
        "distribuicao_notas_global": {
          "0_10": 14,
          "10_20": 7,
          "20_30": 7,
          "30_40": 7,
          "40_50": 5,
          "50_60": 40,
          "60_70": 55,
          "70_80": 34,
          "80_90": 23,
          "90_100": 0
        }
      },
      {
        "codigo_disciplina": "SIN 132",
        "disciplina": "MATEMÁTICA DISCRETA",
        "carga_horaria": 60,
        "dados_agregados": {
          "total_estudantes": 1209,
          "aprovacoes": 567,
          "reprovacoes": 560,
          "abandonos": 82,
          "media_nota_global": 46.4,
          "menor_nota_global": 1,
          "maior_nota_global": 99
        },
        "componentes_idd": {
          "taxa_reprovacao_global": 0.4632,
          "taxa_abandono_global": 0.0678,
          "media_nota_global": 46.4,
          "media_nota_normalizada": 0.536,
          "proporcao_notas_baixas": 0.6203,
          "consistencia_historica": {
            "valor_normalizado": 0.5786,
            "desvio_padrao_tr": 0.1054,
            "limiar_normalizacao": 0.25
          }
        },
        "indicadores": {
          "taxa_reprovacao": 0.4632,
          "taxa_abandono": 0.0678,
          "proporcao_notas_baixas": 0.6203,
          "consistencia_historica": 0.5786,
          "indice_dificuldade": 0.4338
        },
        "distribuicao_notas_global": {
          "0_10": 152,
          "10_20": 112,
          "20_30": 107,
          "30_40": 98,
          "40_50": 108,
          "50_60": 173,
          "60_70": 233,
          "70_80": 139,
          "80_90": 65,
          "90_100": 0
        }
      },
      {
        "codigo_disciplina": "SIN 141",
        "disciplina": "COMPUTAÇÃO ORIENTADA A OBJETOS",
        "carga_horaria": 60,
        "dados_agregados": {
          "total_estudantes": 1015,
          "aprovacoes": 593,
          "reprovacoes": 363,
          "abandonos": 59,
          "media_nota_global": 50.55,
          "menor_nota_global": 1,
          "maior_nota_global": 100
        },
        "componentes_idd": {
          "taxa_reprovacao_global": 0.3576,
          "taxa_abandono_global": 0.0581,
          "media_nota_global": 50.55,
          "media_nota_normalizada": 0.4945,
          "proporcao_notas_baixas": 0.4798,
          "consistencia_historica": {
            "valor_normalizado": 0.4389,
            "desvio_padrao_tr": 0.1403,
            "limiar_normalizacao": 0.25
          }
        },
        "indicadores": {
          "taxa_reprovacao": 0.3576,
          "taxa_abandono": 0.0581,
          "proporcao_notas_baixas": 0.4798,
          "consistencia_historica": 0.4389,
          "indice_dificuldade": 0.3516
        },
        "distribuicao_notas_global": {
          "0_10": 172,
          "10_20": 74,
          "20_30": 55,
          "30_40": 45,
          "40_50": 42,
          "50_60": 99,
          "60_70": 202,
          "70_80": 189,
          "80_90": 103,
          "90_100": 0
        }
      },
      {
        "codigo_disciplina": "SIN 142",
        "disciplina": "PROGRAMAÇÃO CONCORRENTE E DISTRIBUÍDA",
        "carga_horaria": 30,
        "dados_agregados": {
          "total_estudantes": 368,
          "aprovacoes": 337,
          "reprovacoes": 29,
          "abandonos": 2,
          "media_nota_global": 71.98,
          "menor_nota_global": 9,
          "maior_nota_global": 100
        },
        "componentes_idd": {
          "taxa_reprovacao_global": 0.0788,
          "taxa_abandono_global": 0.0054,
          "media_nota_global": 71.98,
          "media_nota_normalizada": 0.2802,
          "proporcao_notas_baixas": 0.1957,
          "consistencia_historica": {
            "valor_normalizado": 0.7192,
            "desvio_padrao_tr": 0.0702,
            "limiar_normalizacao": 0.25
          }
        },
        "indicadores": {
          "taxa_reprovacao": 0.0788,
          "taxa_abandono": 0.0054,
          "proporcao_notas_baixas": 0.1957,
          "consistencia_historica": 0.7192,
          "indice_dificuldade": 0.186
        },
        "distribuicao_notas_global": {
          "0_10": 7,
          "10_20": 1,
          "20_30": 5,
          "30_40": 9,
          "40_50": 5,
          "50_60": 45,
          "60_70": 96,
          "70_80": 75,
          "80_90": 67,
          "90_100": 0
        }
      },
      {
        "codigo_disciplina": "SIN 142",
        "disciplina": "SISTEMAS DISTRIBUÍDOS",
        "carga_horaria": 60,
        "dados_agregados": {
          "total_estudantes": 100,
          "aprovacoes": 90,
          "reprovacoes": 7,
          "abandonos": 3,
          "media_nota_global": 67.25,
          "menor_nota_global": 1,
          "maior_nota_global": 100
        },
        "componentes_idd": {
          "taxa_reprovacao_global": 0.07,
          "taxa_abandono_global": 0.03,
          "media_nota_global": 67.25,
          "media_nota_normalizada": 0.3275,
          "proporcao_notas_baixas": 0.17,
          "consistencia_historica": {
            "valor_normalizado": 0,
            "desvio_padrao_tr": 0.2544,
            "limiar_normalizacao": 0.25
          }
        },
        "indicadores": {
          "taxa_reprovacao": 0.07,
          "taxa_abandono": 0.03,
          "proporcao_notas_baixas": 0.17,
          "consistencia_historica": 0,
          "indice_dificuldade": 0.1215
        },
        "distribuicao_notas_global": {
          "0_10": 1,
          "10_20": 3,
          "20_30": 1,
          "30_40": 2,
          "40_50": 3,
          "50_60": 7,
          "60_70": 32,
          "70_80": 39,
          "80_90": 10,
          "90_100": 0
        }
      },
      {
        "codigo_disciplina": "SIN 143",
        "disciplina": "LABORATÓRIO DE PROGRAMAÇÃO",
        "carga_horaria": 60,
        "dados_agregados": {
          "total_estudantes": 516,
          "aprovacoes": 484,
          "reprovacoes": 24,
          "abandonos": 8,
          "media_nota_global": 77.06,
          "menor_nota_global": 1,
          "maior_nota_global": 100
        },
        "componentes_idd": {
          "taxa_reprovacao_global": 0.0465,
          "taxa_abandono_global": 0.0155,
          "media_nota_global": 77.06,
          "media_nota_normalizada": 0.2294,
          "proporcao_notas_baixas": 0.1337,
          "consistencia_historica": {
            "valor_normalizado": 0.7712,
            "desvio_padrao_tr": 0.0572,
            "limiar_normalizacao": 0.25
          }
        },
        "indicadores": {
          "taxa_reprovacao": 0.0465,
          "taxa_abandono": 0.0155,
          "proporcao_notas_baixas": 0.1337,
          "consistencia_historica": 0.7712,
          "indice_dificuldade": 0.1624
        },
        "distribuicao_notas_global": {
          "0_10": 13,
          "10_20": 3,
          "20_30": 5,
          "30_40": 4,
          "40_50": 3,
          "50_60": 41,
          "60_70": 80,
          "70_80": 125,
          "80_90": 96,
          "90_100": 0
        }
      },
      {
        "codigo_disciplina": "SIN 211",
        "disciplina": "ALGORITMOS E ESTRUTURAS DE DADOS I",
        "carga_horaria": 90,
        "dados_agregados": {
          "total_estudantes": 146,
          "aprovacoes": 72,
          "reprovacoes": 62,
          "abandonos": 12,
          "media_nota_global": 47.01,
          "menor_nota_global": 1,
          "maior_nota_global": 100
        },
        "componentes_idd": {
          "taxa_reprovacao_global": 0.4247,
          "taxa_abandono_global": 0.0822,
          "media_nota_global": 47.01,
          "media_nota_normalizada": 0.5299,
          "proporcao_notas_baixas": 0.5479,
          "consistencia_historica": {
            "valor_normalizado": 0.6875,
            "desvio_padrao_tr": 0.0781,
            "limiar_normalizacao": 0.25
          }
        },
        "indicadores": {
          "taxa_reprovacao": 0.4247,
          "taxa_abandono": 0.0822,
          "proporcao_notas_baixas": 0.5479,
          "consistencia_historica": 0.6875,
          "indice_dificuldade": 0.422
        },
        "distribuicao_notas_global": {
          "0_10": 24,
          "10_20": 12,
          "20_30": 14,
          "30_40": 9,
          "40_50": 9,
          "50_60": 12,
          "60_70": 25,
          "70_80": 24,
          "80_90": 11,
          "90_100": 0
        }
      },
      {
        "codigo_disciplina": "SIN 211",
        "disciplina": "ALGORITMOS E ESTRUTURAS DE DADOS",
        "carga_horaria": 90,
        "dados_agregados": {
          "total_estudantes": 1361,
          "aprovacoes": 811,
          "reprovacoes": 453,
          "abandonos": 97,
          "media_nota_global": 52.21,
          "menor_nota_global": 1,
          "maior_nota_global": 100
        },
        "componentes_idd": {
          "taxa_reprovacao_global": 0.3328,
          "taxa_abandono_global": 0.0713,
          "media_nota_global": 52.21,
          "media_nota_normalizada": 0.4779,
          "proporcao_notas_baixas": 0.4842,
          "consistencia_historica": {
            "valor_normalizado": 0.5325,
            "desvio_padrao_tr": 0.1169,
            "limiar_normalizacao": 0.25
          }
        },
        "indicadores": {
          "taxa_reprovacao": 0.3328,
          "taxa_abandono": 0.0713,
          "proporcao_notas_baixas": 0.4842,
          "consistencia_historica": 0.5325,
          "indice_dificuldade": 0.3522
        },
        "distribuicao_notas_global": {
          "0_10": 173,
          "10_20": 91,
          "20_30": 76,
          "30_40": 80,
          "40_50": 69,
          "50_60": 170,
          "60_70": 287,
          "70_80": 249,
          "80_90": 134,
          "90_100": 0
        }
      },
      {
        "codigo_disciplina": "SIN 213",
        "disciplina": "PROJETO DE ALGORITMOS",
        "carga_horaria": 90,
        "dados_agregados": {
          "total_estudantes": 462,
          "aprovacoes": 399,
          "reprovacoes": 52,
          "abandonos": 11,
          "media_nota_global": 65.94,
          "menor_nota_global": 1,
          "maior_nota_global": 98
        },
        "componentes_idd": {
          "taxa_reprovacao_global": 0.1126,
          "taxa_abandono_global": 0.0238,
          "media_nota_global": 65.94,
          "media_nota_normalizada": 0.3406,
          "proporcao_notas_baixas": 0.2532,
          "consistencia_historica": {
            "valor_normalizado": 0.6618,
            "desvio_padrao_tr": 0.0846,
            "limiar_normalizacao": 0.25
          }
        },
        "indicadores": {
          "taxa_reprovacao": 0.1126,
          "taxa_abandono": 0.0238,
          "proporcao_notas_baixas": 0.2532,
          "consistencia_historica": 0.6618,
          "indice_dificuldade": 0.2164
        },
        "distribuicao_notas_global": {
          "0_10": 14,
          "10_20": 13,
          "20_30": 10,
          "30_40": 7,
          "40_50": 12,
          "50_60": 61,
          "60_70": 136,
          "70_80": 121,
          "80_90": 68,
          "90_100": 0
        }
      },
      {
        "codigo_disciplina": "SIN 220",
        "disciplina": "BANCO DE DADOS",
        "carga_horaria": 60,
        "dados_agregados": {
          "total_estudantes": 939,
          "aprovacoes": 624,
          "reprovacoes": 223,
          "abandonos": 92,
          "media_nota_global": 58.79,
          "menor_nota_global": 1,
          "maior_nota_global": 99
        },
        "componentes_idd": {
          "taxa_reprovacao_global": 0.2375,
          "taxa_abandono_global": 0.098,
          "media_nota_global": 58.79,
          "media_nota_normalizada": 0.4121,
          "proporcao_notas_baixas": 0.3876,
          "consistencia_historica": {
            "valor_normalizado": 0.6138,
            "desvio_padrao_tr": 0.0966,
            "limiar_normalizacao": 0.25
          }
        },
        "indicadores": {
          "taxa_reprovacao": 0.2375,
          "taxa_abandono": 0.098,
          "proporcao_notas_baixas": 0.3876,
          "consistencia_historica": 0.6138,
          "indice_dificuldade": 0.3047
        },
        "distribuicao_notas_global": {
          "0_10": 71,
          "10_20": 54,
          "20_30": 36,
          "30_40": 40,
          "40_50": 65,
          "50_60": 98,
          "60_70": 203,
          "70_80": 183,
          "80_90": 138,
          "90_100": 0
        }
      },
      {
        "codigo_disciplina": "SIN 221",
        "disciplina": "ENGENHARIA DE SOFTWARE I",
        "carga_horaria": 60,
        "dados_agregados": {
          "total_estudantes": 925,
          "aprovacoes": 732,
          "reprovacoes": 152,
          "abandonos": 41,
          "media_nota_global": 64.84,
          "menor_nota_global": 3,
          "maior_nota_global": 100
        },
        "componentes_idd": {
          "taxa_reprovacao_global": 0.1643,
          "taxa_abandono_global": 0.0443,
          "media_nota_global": 64.84,
          "media_nota_normalizada": 0.3516,
          "proporcao_notas_baixas": 0.2605,
          "consistencia_historica": {
            "valor_normalizado": 0.6929,
            "desvio_padrao_tr": 0.0768,
            "limiar_normalizacao": 0.25
          }
        },
        "indicadores": {
          "taxa_reprovacao": 0.1643,
          "taxa_abandono": 0.0443,
          "proporcao_notas_baixas": 0.2605,
          "consistencia_historica": 0.6929,
          "indice_dificuldade": 0.2451
        },
        "distribuicao_notas_global": {
          "0_10": 52,
          "10_20": 21,
          "20_30": 28,
          "30_40": 24,
          "40_50": 38,
          "50_60": 78,
          "60_70": 196,
          "70_80": 262,
          "80_90": 179,
          "90_100": 0
        }
      },
      {
        "codigo_disciplina": "SIN 222",
        "disciplina": "FUNDAMENTOS DE SISTEMAS DE INFORMAÇÃO",
        "carga_horaria": 60,
        "dados_agregados": {
          "total_estudantes": 1203,
          "aprovacoes": 948,
          "reprovacoes": 136,
          "abandonos": 119,
          "media_nota_global": 62.66,
          "menor_nota_global": 1,
          "maior_nota_global": 96
        },
        "componentes_idd": {
          "taxa_reprovacao_global": 0.1131,
          "taxa_abandono_global": 0.0989,
          "media_nota_global": 62.66,
          "media_nota_normalizada": 0.3734,
          "proporcao_notas_baixas": 0.2826,
          "consistencia_historica": {
            "valor_normalizado": 0.7573,
            "desvio_padrao_tr": 0.0607,
            "limiar_normalizacao": 0.25
          }
        },
        "indicadores": {
          "taxa_reprovacao": 0.1131,
          "taxa_abandono": 0.0989,
          "proporcao_notas_baixas": 0.2826,
          "consistencia_historica": 0.7573,
          "indice_dificuldade": 0.2522
        },
        "distribuicao_notas_global": {
          "0_10": 64,
          "10_20": 31,
          "20_30": 33,
          "30_40": 30,
          "40_50": 51,
          "50_60": 131,
          "60_70": 363,
          "70_80": 310,
          "80_90": 173,
          "90_100": 0
        }
      },
      {
        "codigo_disciplina": "SIN 251",
        "disciplina": "ORGANIZAÇÃO DE COMPUTADORES",
        "carga_horaria": 60,
        "dados_agregados": {
          "total_estudantes": 916,
          "aprovacoes": 645,
          "reprovacoes": 234,
          "abandonos": 37,
          "media_nota_global": 60.6,
          "menor_nota_global": 1,
          "maior_nota_global": 100
        },
        "componentes_idd": {
          "taxa_reprovacao_global": 0.2555,
          "taxa_abandono_global": 0.0404,
          "media_nota_global": 60.6,
          "media_nota_normalizada": 0.394,
          "proporcao_notas_baixas": 0.3755,
          "consistencia_historica": {
            "valor_normalizado": 0.2925,
            "desvio_padrao_tr": 0.1769,
            "limiar_normalizacao": 0.25
          }
        },
        "indicadores": {
          "taxa_reprovacao": 0.2555,
          "taxa_abandono": 0.0404,
          "proporcao_notas_baixas": 0.3755,
          "consistencia_historica": 0.2925,
          "indice_dificuldade": 0.2619
        },
        "distribuicao_notas_global": {
          "0_10": 41,
          "10_20": 29,
          "20_30": 40,
          "30_40": 54,
          "40_50": 62,
          "50_60": 118,
          "60_70": 230,
          "70_80": 201,
          "80_90": 97,
          "90_100": 0
        }
      },
      {
        "codigo_disciplina": "SIN 252",
        "disciplina": "ARQUITETURA DE COMPUTADORES",
        "carga_horaria": 60,
        "dados_agregados": {
          "total_estudantes": 672,
          "aprovacoes": 496,
          "reprovacoes": 141,
          "abandonos": 35,
          "media_nota_global": 62.68,
          "menor_nota_global": 2,
          "maior_nota_global": 100
        },
        "componentes_idd": {
          "taxa_reprovacao_global": 0.2098,
          "taxa_abandono_global": 0.0521,
          "media_nota_global": 62.68,
          "media_nota_normalizada": 0.3732,
          "proporcao_notas_baixas": 0.317,
          "consistencia_historica": {
            "valor_normalizado": 0.5738,
            "desvio_padrao_tr": 0.1066,
            "limiar_normalizacao": 0.25
          }
        },
        "indicadores": {
          "taxa_reprovacao": 0.2098,
          "taxa_abandono": 0.0521,
          "proporcao_notas_baixas": 0.317,
          "consistencia_historica": 0.5738,
          "indice_dificuldade": 0.2634
        },
        "distribuicao_notas_global": {
          "0_10": 37,
          "10_20": 23,
          "20_30": 21,
          "30_40": 29,
          "40_50": 35,
          "50_60": 68,
          "60_70": 163,
          "70_80": 152,
          "80_90": 99,
          "90_100": 0
        }
      },
      {
        "codigo_disciplina": "SIN 320",
        "disciplina": "LABORATÓRIO DE BANCO DE DADOS",
        "carga_horaria": 60,
        "dados_agregados": {
          "total_estudantes": 609,
          "aprovacoes": 540,
          "reprovacoes": 52,
          "abandonos": 17,
          "media_nota_global": 72.14,
          "menor_nota_global": 2,
          "maior_nota_global": 100
        },
        "componentes_idd": {
          "taxa_reprovacao_global": 0.0854,
          "taxa_abandono_global": 0.0279,
          "media_nota_global": 72.14,
          "media_nota_normalizada": 0.2786,
          "proporcao_notas_baixas": 0.1724,
          "consistencia_historica": {
            "valor_normalizado": 0.7663,
            "desvio_padrao_tr": 0.0584,
            "limiar_normalizacao": 0.25
          }
        },
        "indicadores": {
          "taxa_reprovacao": 0.0854,
          "taxa_abandono": 0.0279,
          "proporcao_notas_baixas": 0.1724,
          "consistencia_historica": 0.7663,
          "indice_dificuldade": 0.1937
        },
        "distribuicao_notas_global": {
          "0_10": 9,
          "10_20": 6,
          "20_30": 7,
          "30_40": 10,
          "40_50": 8,
          "50_60": 65,
          "60_70": 137,
          "70_80": 157,
          "80_90": 145,
          "90_100": 0
        }
      },
      {
        "codigo_disciplina": "SIN 321",
        "disciplina": "ENGENHARIA DE SOFTWARE II",
        "carga_horaria": 60,
        "dados_agregados": {
          "total_estudantes": 644,
          "aprovacoes": 585,
          "reprovacoes": 48,
          "abandonos": 11,
          "media_nota_global": 74.82,
          "menor_nota_global": 13,
          "maior_nota_global": 100
        },
        "componentes_idd": {
          "taxa_reprovacao_global": 0.0745,
          "taxa_abandono_global": 0.0171,
          "media_nota_global": 74.82,
          "media_nota_normalizada": 0.2518,
          "proporcao_notas_baixas": 0.1196,
          "consistencia_historica": {
            "valor_normalizado": 0.6554,
            "desvio_padrao_tr": 0.0862,
            "limiar_normalizacao": 0.25
          }
        },
        "indicadores": {
          "taxa_reprovacao": 0.0745,
          "taxa_abandono": 0.0171,
          "proporcao_notas_baixas": 0.1196,
          "consistencia_historica": 0.6554,
          "indice_dificuldade": 0.1633
        },
        "distribuicao_notas_global": {
          "0_10": 11,
          "10_20": 3,
          "20_30": 4,
          "30_40": 8,
          "40_50": 10,
          "50_60": 41,
          "60_70": 116,
          "70_80": 154,
          "80_90": 227,
          "90_100": 0
        }
      },
      {
        "codigo_disciplina": "SIN 322",
        "disciplina": "PRÁTICA E GERENCIAMENTO DE PROJETOS",
        "carga_horaria": 30,
        "dados_agregados": {
          "total_estudantes": 168,
          "aprovacoes": 163,
          "reprovacoes": 2,
          "abandonos": 3,
          "media_nota_global": 80.64,
          "menor_nota_global": 13,
          "maior_nota_global": 100
        },
        "componentes_idd": {
          "taxa_reprovacao_global": 0.0119,
          "taxa_abandono_global": 0.0179,
          "media_nota_global": 80.64,
          "media_nota_normalizada": 0.1936,
          "proporcao_notas_baixas": 0.0476,
          "consistencia_historica": {
            "valor_normalizado": 0.9523,
            "desvio_padrao_tr": 0.0119,
            "limiar_normalizacao": 0.25
          }
        },
        "indicadores": {
          "taxa_reprovacao": 0.0119,
          "taxa_abandono": 0.0179,
          "proporcao_notas_baixas": 0.0476,
          "consistencia_historica": 0.9523,
          "indice_dificuldade": 0.1488
        },
        "distribuicao_notas_global": {
          "0_10": 1,
          "10_20": 2,
          "20_30": 2,
          "30_40": 0,
          "40_50": 0,
          "50_60": 3,
          "60_70": 11,
          "70_80": 44,
          "80_90": 65,
          "90_100": 0
        }
      },
      {
        "codigo_disciplina": "SIN 322",
        "disciplina": "PRÁTICA DE GERENCIAMENTO DE PROJETOS",
        "carga_horaria": 30,
        "dados_agregados": {
          "total_estudantes": 410,
          "aprovacoes": 393,
          "reprovacoes": 11,
          "abandonos": 6,
          "media_nota_global": 77.16,
          "menor_nota_global": 6,
          "maior_nota_global": 100
        },
        "componentes_idd": {
          "taxa_reprovacao_global": 0.0268,
          "taxa_abandono_global": 0.0146,
          "media_nota_global": 77.16,
          "media_nota_normalizada": 0.2284,
          "proporcao_notas_baixas": 0.078,
          "consistencia_historica": {
            "valor_normalizado": 0.9157,
            "desvio_padrao_tr": 0.0211,
            "limiar_normalizacao": 0.25
          }
        },
        "indicadores": {
          "taxa_reprovacao": 0.0268,
          "taxa_abandono": 0.0146,
          "proporcao_notas_baixas": 0.078,
          "consistencia_historica": 0.9157,
          "indice_dificuldade": 0.1613
        },
        "distribuicao_notas_global": {
          "0_10": 5,
          "10_20": 1,
          "20_30": 2,
          "30_40": 1,
          "40_50": 3,
          "50_60": 20,
          "60_70": 69,
          "70_80": 135,
          "80_90": 95,
          "90_100": 0
        }
      },
      {
        "codigo_disciplina": "SIN 323",
        "disciplina": "INTELIGÊNCIA ARTIFICIAL",
        "carga_horaria": 60,
        "dados_agregados": {
          "total_estudantes": 683,
          "aprovacoes": 433,
          "reprovacoes": 202,
          "abandonos": 48,
          "media_nota_global": 55.26,
          "menor_nota_global": 1,
          "maior_nota_global": 97
        },
        "componentes_idd": {
          "taxa_reprovacao_global": 0.2958,
          "taxa_abandono_global": 0.0703,
          "media_nota_global": 55.26,
          "media_nota_normalizada": 0.4474,
          "proporcao_notas_baixas": 0.4305,
          "consistencia_historica": {
            "valor_normalizado": 0.4195,
            "desvio_padrao_tr": 0.1451,
            "limiar_normalizacao": 0.25
          }
        },
        "indicadores": {
          "taxa_reprovacao": 0.2958,
          "taxa_abandono": 0.0703,
          "proporcao_notas_baixas": 0.4305,
          "consistencia_historica": 0.4195,
          "indice_dificuldade": 0.3136
        },
        "distribuicao_notas_global": {
          "0_10": 67,
          "10_20": 28,
          "20_30": 34,
          "30_40": 43,
          "40_50": 45,
          "50_60": 77,
          "60_70": 175,
          "70_80": 126,
          "80_90": 66,
          "90_100": 0
        }
      },
      {
        "codigo_disciplina": "SIN 351",
        "disciplina": "SISTEMAS OPERACIONAIS",
        "carga_horaria": 60,
        "dados_agregados": {
          "total_estudantes": 653,
          "aprovacoes": 441,
          "reprovacoes": 200,
          "abandonos": 12,
          "media_nota_global": 57.66,
          "menor_nota_global": 1,
          "maior_nota_global": 99
        },
        "componentes_idd": {
          "taxa_reprovacao_global": 0.3063,
          "taxa_abandono_global": 0.0184,
          "media_nota_global": 57.66,
          "media_nota_normalizada": 0.4234,
          "proporcao_notas_baixas": 0.4717,
          "consistencia_historica": {
            "valor_normalizado": 0.2602,
            "desvio_padrao_tr": 0.185,
            "limiar_normalizacao": 0.25
          }
        },
        "indicadores": {
          "taxa_reprovacao": 0.3063,
          "taxa_abandono": 0.0184,
          "proporcao_notas_baixas": 0.4717,
          "consistencia_historica": 0.2602,
          "indice_dificuldade": 0.2923
        },
        "distribuicao_notas_global": {
          "0_10": 23,
          "10_20": 18,
          "20_30": 25,
          "30_40": 47,
          "40_50": 60,
          "50_60": 135,
          "60_70": 193,
          "70_80": 95,
          "80_90": 50,
          "90_100": 0
        }
      },
      {
        "codigo_disciplina": "SIN 392",
        "disciplina": "INTRODUÇÃO AO PROCESSAMENTO DIGITAL DE IMAGENS",
        "carga_horaria": 60,
        "dados_agregados": {
          "total_estudantes": 454,
          "aprovacoes": 399,
          "reprovacoes": 49,
          "abandonos": 6,
          "media_nota_global": 70.5,
          "menor_nota_global": 3,
          "maior_nota_global": 99
        },
        "componentes_idd": {
          "taxa_reprovacao_global": 0.1079,
          "taxa_abandono_global": 0.0132,
          "media_nota_global": 70.5,
          "media_nota_normalizada": 0.295,
          "proporcao_notas_baixas": 0.1872,
          "consistencia_historica": {
            "valor_normalizado": 0.0575,
            "desvio_padrao_tr": 0.2356,
            "limiar_normalizacao": 0.25
          }
        },
        "indicadores": {
          "taxa_reprovacao": 0.1079,
          "taxa_abandono": 0.0132,
          "proporcao_notas_baixas": 0.1872,
          "consistencia_historica": 0.0575,
          "indice_dificuldade": 0.1333
        },
        "distribuicao_notas_global": {
          "0_10": 8,
          "10_20": 12,
          "20_30": 8,
          "30_40": 6,
          "40_50": 13,
          "50_60": 38,
          "60_70": 106,
          "70_80": 116,
          "80_90": 98,
          "90_100": 0
        }
      },
      {
        "codigo_disciplina": "SIN 421",
        "disciplina": "INTERAÇÃO HUMANO-COMPUTADOR",
        "carga_horaria": 60,
        "dados_agregados": {
          "total_estudantes": 599,
          "aprovacoes": 581,
          "reprovacoes": 6,
          "abandonos": 12,
          "media_nota_global": 78.73,
          "menor_nota_global": 3,
          "maior_nota_global": 100
        },
        "componentes_idd": {
          "taxa_reprovacao_global": 0.01,
          "taxa_abandono_global": 0.02,
          "media_nota_global": 78.73,
          "media_nota_normalizada": 0.2127,
          "proporcao_notas_baixas": 0.0434,
          "consistencia_historica": {
            "valor_normalizado": 0.9421,
            "desvio_padrao_tr": 0.0145,
            "limiar_normalizacao": 0.25
          }
        },
        "indicadores": {
          "taxa_reprovacao": 0.01,
          "taxa_abandono": 0.02,
          "proporcao_notas_baixas": 0.0434,
          "consistencia_historica": 0.9421,
          "indice_dificuldade": 0.1508
        },
        "distribuicao_notas_global": {
          "0_10": 10,
          "10_20": 4,
          "20_30": 0,
          "30_40": 1,
          "40_50": 2,
          "50_60": 9,
          "60_70": 67,
          "70_80": 187,
          "80_90": 224,
          "90_100": 0
        }
      },
      {
        "codigo_disciplina": "SIN 422",
        "disciplina": "QUALIDADE DE SOFTWARE",
        "carga_horaria": 60,
        "dados_agregados": {
          "total_estudantes": 317,
          "aprovacoes": 302,
          "reprovacoes": 1,
          "abandonos": 14,
          "media_nota_global": 78.81,
          "menor_nota_global": 11,
          "maior_nota_global": 100
        },
        "componentes_idd": {
          "taxa_reprovacao_global": 0.0032,
          "taxa_abandono_global": 0.0442,
          "media_nota_global": 78.81,
          "media_nota_normalizada": 0.2119,
          "proporcao_notas_baixas": 0.0568,
          "consistencia_historica": {
            "valor_normalizado": 0.9586,
            "desvio_padrao_tr": 0.0103,
            "limiar_normalizacao": 0.25
          }
        },
        "indicadores": {
          "taxa_reprovacao": 0.0032,
          "taxa_abandono": 0.0442,
          "proporcao_notas_baixas": 0.0568,
          "consistencia_historica": 0.9586,
          "indice_dificuldade": 0.1567
        },
        "distribuicao_notas_global": {
          "0_10": 6,
          "10_20": 6,
          "20_30": 2,
          "30_40": 0,
          "40_50": 0,
          "50_60": 4,
          "60_70": 29,
          "70_80": 97,
          "80_90": 116,
          "90_100": 0
        }
      },
      {
        "codigo_disciplina": "SIN 480",
        "disciplina": "PESQUISA OPERACIONAL I",
        "carga_horaria": 60,
        "dados_agregados": {
          "total_estudantes": 766,
          "aprovacoes": 644,
          "reprovacoes": 105,
          "abandonos": 17,
          "media_nota_global": 67.76,
          "menor_nota_global": 2,
          "maior_nota_global": 100
        },
        "componentes_idd": {
          "taxa_reprovacao_global": 0.1371,
          "taxa_abandono_global": 0.0222,
          "media_nota_global": 67.76,
          "media_nota_normalizada": 0.3224,
          "proporcao_notas_baixas": 0.2598,
          "consistencia_historica": {
            "valor_normalizado": 0.6346,
            "desvio_padrao_tr": 0.0913,
            "limiar_normalizacao": 0.25
          }
        },
        "indicadores": {
          "taxa_reprovacao": 0.1371,
          "taxa_abandono": 0.0222,
          "proporcao_notas_baixas": 0.2598,
          "consistencia_historica": 0.6346,
          "indice_dificuldade": 0.2193
        },
        "distribuicao_notas_global": {
          "0_10": 23,
          "10_20": 10,
          "20_30": 9,
          "30_40": 22,
          "40_50": 29,
          "50_60": 106,
          "60_70": 180,
          "70_80": 186,
          "80_90": 147,
          "90_100": 0
        }
      },
      {
        "codigo_disciplina": "SIN 496",
        "disciplina": "ATIVIDADES COMPLEMENTARES",
        "carga_horaria": 180,
        "dados_agregados": {
          "total_estudantes": 515,
          "aprovacoes": 359,
          "reprovacoes": 41,
          "abandonos": 0,
          "media_nota_global": 25.87,
          "menor_nota_global": 50,
          "maior_nota_global": 100
        },
        "componentes_idd": {
          "taxa_reprovacao_global": 0.0796,
          "taxa_abandono_global": 0,
          "media_nota_global": 25.87,
          "media_nota_normalizada": 0.7413,
          "proporcao_notas_baixas": 0.7262,
          "consistencia_historica": {
            "valor_normalizado": 0.6227,
            "desvio_padrao_tr": 0.0943,
            "limiar_normalizacao": 0.25
          }
        },
        "indicadores": {
          "taxa_reprovacao": 0.0796,
          "taxa_abandono": 0,
          "proporcao_notas_baixas": 0.7262,
          "consistencia_historica": 0.6227,
          "indice_dificuldade": 0.3473
        },
        "distribuicao_notas_global": {
          "0_10": 373,
          "10_20": 0,
          "20_30": 0,
          "30_40": 0,
          "40_50": 1,
          "50_60": 0,
          "60_70": 0,
          "70_80": 0,
          "80_90": 0,
          "90_100": 0
        }
      },
      {
        "codigo_disciplina": "SIN 498",
        "disciplina": "TRABALHO DE CONCLUSÃO DE CURSO I",
        "carga_horaria": 210,
        "dados_agregados": {
          "total_estudantes": 465,
          "aprovacoes": 402,
          "reprovacoes": 5,
          "abandonos": 0,
          "media_nota_global": 58.05,
          "menor_nota_global": 60,
          "maior_nota_global": 100
        },
        "componentes_idd": {
          "taxa_reprovacao_global": 0.0108,
          "taxa_abandono_global": 0,
          "media_nota_global": 58.05,
          "media_nota_normalizada": 0.4195,
          "proporcao_notas_baixas": 0.3505,
          "consistencia_historica": {
            "valor_normalizado": 0.9019,
            "desvio_padrao_tr": 0.0245,
            "limiar_normalizacao": 0.25
          }
        },
        "indicadores": {
          "taxa_reprovacao": 0.0108,
          "taxa_abandono": 0,
          "proporcao_notas_baixas": 0.3505,
          "consistencia_historica": 0.9019,
          "indice_dificuldade": 0.2304
        },
        "distribuicao_notas_global": {
          "0_10": 161,
          "10_20": 0,
          "20_30": 0,
          "30_40": 0,
          "40_50": 0,
          "50_60": 2,
          "60_70": 11,
          "70_80": 46,
          "80_90": 104,
          "90_100": 0
        }
      },
      {
        "codigo_disciplina": "SIN 499",
        "disciplina": "TRABALHO DE CONCLUSÃO DE CURSO II",
        "carga_horaria": 210,
        "dados_agregados": {
          "total_estudantes": 550,
          "aprovacoes": 339,
          "reprovacoes": 35,
          "abandonos": 0,
          "media_nota_global": 40.31,
          "menor_nota_global": 80,
          "maior_nota_global": 100
        },
        "componentes_idd": {
          "taxa_reprovacao_global": 0.0636,
          "taxa_abandono_global": 0,
          "media_nota_global": 40.31,
          "media_nota_normalizada": 0.5969,
          "proporcao_notas_baixas": 0.5655,
          "consistencia_historica": {
            "valor_normalizado": 0.768,
            "desvio_padrao_tr": 0.058,
            "limiar_normalizacao": 0.25
          }
        },
        "indicadores": {
          "taxa_reprovacao": 0.0636,
          "taxa_abandono": 0,
          "proporcao_notas_baixas": 0.5655,
          "consistencia_historica": 0.768,
          "indice_dificuldade": 0.3033
        },
        "distribuicao_notas_global": {
          "0_10": 311,
          "10_20": 0,
          "20_30": 0,
          "30_40": 0,
          "40_50": 0,
          "50_60": 0,
          "60_70": 0,
          "70_80": 25,
          "80_90": 5,
          "90_100": 0
        }
      }
    ],
    "/disciplinas/resumo": [
      {
        "codigo_disciplina": "ADE 104",
        "disciplina": "TEORIA GERAL DA ADMINISTRAÇÃO",
        "taxa_reprovacao": 0.1147,
        "indice_dificuldade": 0.2261
      },
      {
        "codigo_disciplina": "ADE 190",
        "disciplina": "INTRODUÇÃO À ECONOMIA",
        "taxa_reprovacao": 0.1266,
        "indice_dificuldade": 0.2201
      },
      {
        "codigo_disciplina": "ADE 327",
        "disciplina": "EMPREENDEDORISMO",
        "taxa_reprovacao": 0.0342,
        "indice_dificuldade": 0.1681
      },
      {
        "codigo_disciplina": "CIC 100",
        "disciplina": "CONTABILIDADE GERAL",
        "taxa_reprovacao": 0.2888,
        "indice_dificuldade": 0.3632
      },
      {
        "codigo_disciplina": "CRP 199",
        "disciplina": "CÁLCULO DIFERENCIAL E INTEGRAL",
        "taxa_reprovacao": 0.5306,
        "indice_dificuldade": 0.5157
      },
      {
        "codigo_disciplina": "CRP 199",
        "disciplina": "CÁLCULO I",
        "taxa_reprovacao": 0.4673,
        "indice_dificuldade": 0.4474
      },
      {
        "codigo_disciplina": "CRP 297",
        "disciplina": "SOCIOLOGIA GERAL",
        "taxa_reprovacao": 0.2553,
        "indice_dificuldade": 0.3071
      },
      {
        "codigo_disciplina": "CRP 298",
        "disciplina": "GEOMETRIA ANALÍTICA E ÁLGEBRA LINEAR",
        "taxa_reprovacao": 0.4561,
        "indice_dificuldade": 0.4308
      },
      {
        "codigo_disciplina": "ESP 105",
        "disciplina": "INICIAÇÃO À ESTATÍSTICA",
        "taxa_reprovacao": 0.2346,
        "indice_dificuldade": 0.2951
      },
      {
        "codigo_disciplina": "SIN 100",
        "disciplina": "TRATAMENTO E ANÁLISE DE DADOS/INFORMAÇÕES",
        "taxa_reprovacao": 0.1203,
        "indice_dificuldade": 0.2327
      },
      {
        "codigo_disciplina": "SIN 101",
        "disciplina": "INFORMÁTICA E SOCIEDADE",
        "taxa_reprovacao": 0.0694,
        "indice_dificuldade": 0.2034
      },
      {
        "codigo_disciplina": "SIN 110",
        "disciplina": "PROGRAMAÇÃO I",
        "taxa_reprovacao": 0.4253,
        "indice_dificuldade": 0.4428
      },
      {
        "codigo_disciplina": "SIN 110",
        "disciplina": "PROGRAMAÇÃO",
        "taxa_reprovacao": 0.478,
        "indice_dificuldade": 0.449
      },
      {
        "codigo_disciplina": "SIN 130",
        "disciplina": "INTRODUÇÃO À LÓGICA",
        "taxa_reprovacao": 0.3465,
        "indice_dificuldade": 0.3531
      },
      {
        "codigo_disciplina": "SIN 131",
        "disciplina": "INTRODUÇÃO À TEORIA DA COMPUTAÇÃO",
        "taxa_reprovacao": 0.3005,
        "indice_dificuldade": 0.2919
      },
      {
        "codigo_disciplina": "SIN 131",
        "disciplina": "INTRODUÇÃO À TEORIA DA COMPUTAÇÃO I",
        "taxa_reprovacao": 0,
        "indice_dificuldade": 0.1286
      },
      {
        "codigo_disciplina": "SIN 131",
        "disciplina": "INTRODUÇÃO À TEORIA DA  COMPUTAÇÃO",
        "taxa_reprovacao": 0.2172,
        "indice_dificuldade": 0.273
      },
      {
        "codigo_disciplina": "SIN 132",
        "disciplina": "MATEMÁTICA DISCRETA",
        "taxa_reprovacao": 0.4632,
        "indice_dificuldade": 0.4338
      },
      {
        "codigo_disciplina": "SIN 141",
        "disciplina": "COMPUTAÇÃO ORIENTADA A OBJETOS",
        "taxa_reprovacao": 0.3576,
        "indice_dificuldade": 0.3516
      },
      {
        "codigo_disciplina": "SIN 142",
        "disciplina": "PROGRAMAÇÃO CONCORRENTE E DISTRIBUÍDA",
        "taxa_reprovacao": 0.0788,
        "indice_dificuldade": 0.186
      },
      {
        "codigo_disciplina": "SIN 142",
        "disciplina": "SISTEMAS DISTRIBUÍDOS",
        "taxa_reprovacao": 0.07,
        "indice_dificuldade": 0.1215
      },
      {
        "codigo_disciplina": "SIN 143",
        "disciplina": "LABORATÓRIO DE PROGRAMAÇÃO",
        "taxa_reprovacao": 0.0465,
        "indice_dificuldade": 0.1624
      },
      {
        "codigo_disciplina": "SIN 211",
        "disciplina": "ALGORITMOS E ESTRUTURAS DE DADOS I",
        "taxa_reprovacao": 0.4247,
        "indice_dificuldade": 0.422
      },
      {
        "codigo_disciplina": "SIN 211",
        "disciplina": "ALGORITMOS E ESTRUTURAS DE DADOS",
        "taxa_reprovacao": 0.3328,
        "indice_dificuldade": 0.3522
      },
      {
        "codigo_disciplina": "SIN 213",
        "disciplina": "PROJETO DE ALGORITMOS",
        "taxa_reprovacao": 0.1126,
        "indice_dificuldade": 0.2164
      },
      {
        "codigo_disciplina": "SIN 220",
        "disciplina": "BANCO DE DADOS",
        "taxa_reprovacao": 0.2375,
        "indice_dificuldade": 0.3047
      },
      {
        "codigo_disciplina": "SIN 221",
        "disciplina": "ENGENHARIA DE SOFTWARE I",
        "taxa_reprovacao": 0.1643,
        "indice_dificuldade": 0.2451
      },
      {
        "codigo_disciplina": "SIN 222",
        "disciplina": "FUNDAMENTOS DE SISTEMAS DE INFORMAÇÃO",
        "taxa_reprovacao": 0.1131,
        "indice_dificuldade": 0.2522
      },
      {
        "codigo_disciplina": "SIN 251",
        "disciplina": "ORGANIZAÇÃO DE COMPUTADORES",
        "taxa_reprovacao": 0.2555,
        "indice_dificuldade": 0.2619
      },
      {
        "codigo_disciplina": "SIN 252",
        "disciplina": "ARQUITETURA DE COMPUTADORES",
        "taxa_reprovacao": 0.2098,
        "indice_dificuldade": 0.2634
      },
      {
        "codigo_disciplina": "SIN 320",
        "disciplina": "LABORATÓRIO DE BANCO DE DADOS",
        "taxa_reprovacao": 0.0854,
        "indice_dificuldade": 0.1937
      },
      {
        "codigo_disciplina": "SIN 321",
        "disciplina": "ENGENHARIA DE SOFTWARE II",
        "taxa_reprovacao": 0.0745,
        "indice_dificuldade": 0.1633
      },
      {
        "codigo_disciplina": "SIN 322",
        "disciplina": "PRÁTICA E GERENCIAMENTO DE PROJETOS",
        "taxa_reprovacao": 0.0119,
        "indice_dificuldade": 0.1488
      },
      {
        "codigo_disciplina": "SIN 322",
        "disciplina": "PRÁTICA DE GERENCIAMENTO DE PROJETOS",
        "taxa_reprovacao": 0.0268,
        "indice_dificuldade": 0.1613
      },
      {
        "codigo_disciplina": "SIN 323",
        "disciplina": "INTELIGÊNCIA ARTIFICIAL",
        "taxa_reprovacao": 0.2958,
        "indice_dificuldade": 0.3136
      },
      {
        "codigo_disciplina": "SIN 351",
        "disciplina": "SISTEMAS OPERACIONAIS",
        "taxa_reprovacao": 0.3063,
        "indice_dificuldade": 0.2923
      },
      {
        "codigo_disciplina": "SIN 392",
        "disciplina": "INTRODUÇÃO AO PROCESSAMENTO DIGITAL DE IMAGENS",
        "taxa_reprovacao": 0.1079,
        "indice_dificuldade": 0.1333
      },
      {
        "codigo_disciplina": "SIN 421",
        "disciplina": "INTERAÇÃO HUMANO-COMPUTADOR",
        "taxa_reprovacao": 0.01,
        "indice_dificuldade": 0.1508
      },
      {
        "codigo_disciplina": "SIN 422",
        "disciplina": "QUALIDADE DE SOFTWARE",
        "taxa_reprovacao": 0.0032,
        "indice_dificuldade": 0.1567
      },
      {
        "codigo_disciplina": "SIN 480",
        "disciplina": "PESQUISA OPERACIONAL I",
        "taxa_reprovacao": 0.1371,
        "indice_dificuldade": 0.2193
      },
      {
        "codigo_disciplina": "SIN 496",
        "disciplina": "ATIVIDADES COMPLEMENTARES",
        "taxa_reprovacao": 0.0796,
        "indice_dificuldade": 0.3473
      },
      {
        "codigo_disciplina": "SIN 498",
        "disciplina": "TRABALHO DE CONCLUSÃO DE CURSO I",
        "taxa_reprovacao": 0.0108,
        "indice_dificuldade": 0.2304
      },
      {
        "codigo_disciplina": "SIN 499",
        "disciplina": "TRABALHO DE CONCLUSÃO DE CURSO II",
        "taxa_reprovacao": 0.0636,
        "indice_dificuldade": 0.3033
      }
    ],
    "/disciplinas/{codigo}/taxa-reprovacao": {
      "CRP 199": 0.4673,
      "CRP 298": 0.4561,
      "ADE 190": 0.1266,
      "CRP 297": 0.2553,
      "SIN 110": 0.478,
      "SIN 130": 0.3465,
      "SIN 132": 0.4632,
      "SIN 141": 0.3576,
      "SIN 142": 0.07,
      "SIN 220": 0.2375,
      "SIN 221": 0.1643,
      "SIN 222": 0.1131,
      "SIN 251": 0.2555,
      "SIN 252": 0.2098,
      "SIN 100": 0.1203,
      "SIN 101": 0.0694,
      "SIN 131": 0.2172,
      "SIN 143": 0.0465,
      "SIN 211": 0.3328,
      "SIN 320": 0.0854,
      "SIN 321": 0.0745,
      "SIN 351": 0.3063,
      "CIC 100": 0.2888,
      "ADE 104": 0.1147,
      "ADE 327": 0.0342,
      "SIN 322": 0.0268,
      "SIN 323": 0.2958,
      "SIN 421": 0.01,
      "SIN 213": 0.1126,
      "SIN 392": 0.1079,
      "SIN 480": 0.1371,
      "SIN 498": 0.0108,
      "SIN 496": 0.0796,
      "SIN 499": 0.0636,
      "SIN 422": 0.0032,
      "ESP 105": 0.2346
    },
    "/disciplinas/{codigo}/indice-dificuldade": {
      "CRP 199": 0.4474,
      "CRP 298": 0.4308,
      "ADE 190": 0.2201,
      "CRP 297": 0.3071,
      "SIN 110": 0.449,
      "SIN 130": 0.3531,
      "SIN 132": 0.4338,
      "SIN 141": 0.3516,
      "SIN 142": 0.1215,
      "SIN 220": 0.3047,
      "SIN 221": 0.2451,
      "SIN 222": 0.2522,
      "SIN 251": 0.2619,
      "SIN 252": 0.2634,
      "SIN 100": 0.2327,
      "SIN 101": 0.2034,
      "SIN 131": 0.273,
      "SIN 143": 0.1624,
      "SIN 211": 0.3522,
      "SIN 320": 0.1937,
      "SIN 321": 0.1633,
      "SIN 351": 0.2923,
      "CIC 100": 0.3632,
      "ADE 104": 0.2261,
      "ADE 327": 0.1681,
      "SIN 322": 0.1613,
      "SIN 323": 0.3136,
      "SIN 421": 0.1508,
      "SIN 213": 0.2164,
      "SIN 392": 0.1333,
      "SIN 480": 0.2193,
      "SIN 498": 0.2304,
      "SIN 496": 0.3473,
      "SIN 499": 0.3033,
      "SIN 422": 0.1567,
      "ESP 105": 0.2951
    }
  }
}